sphinxcontrib/itemlist/__init__.py
sphinxcontrib_itemlist-1.0.0.dist-info/LICENSE
sphinxcontrib_itemlist-1.0.0.dist-info/METADATA
sphinxcontrib_itemlist-1.0.0.dist-info/WHEEL
sphinxcontrib_itemlist-1.0.0.dist-info/top_level.txt
sphinxcontrib_itemlist-1.0.0.dist-info/RECORD
