Metadata-Version: 2.1
Name: sphinxcontrib-itemlist
Version: 1.0.0
Summary: Sphinx extension to generate a list or table from a sequence of items
Home-page: https://github.com/vhiribarren/sphinxcontrib-itemlist
Author: Vincent Hiribarren
License: MIT
Project-URL: Bug Tracker, https://github.com/vhiribarren/sphinxcontrib-itemlist/issues
Project-URL: Source, https://github.com/vhiribarren/sphinxcontrib-itemlist
Platform: any
Classifier: Development Status :: 4 - Beta
Classifier: Programming Language :: Python :: 3
Classifier: License :: OSI Approved :: MIT License
Classifier: Operating System :: OS Independent
Classifier: Framework :: Sphinx
Classifier: Framework :: Sphinx :: Extension
Classifier: Environment :: Console
Classifier: Environment :: Web Environment
Classifier: Intended Audience :: Developers
Classifier: Topic :: Documentation
Classifier: Topic :: Documentation :: Sphinx
Classifier: Topic :: Software Development :: Documentation
Classifier: Topic :: Text Processing
Classifier: Topic :: Utilities
License-File: LICENSE
Requires-Dist: sphinx
